{
  "비밀이야": [
    {
      "videoId": "ifPOQ-0EQ-E",
      "title": "대왕갈치부터 제철해산물까지 한번에 즐기기 좋은 곳?! | 여의도 파도",
      "date": "2일 전",
      "views": "조회수 4.2만회",
      "url": "https://youtu.be/ifPOQ-0EQ-E"
    },
    {
      "videoId": "XetH267hDeI",
      "title": "🔥흑백요리사 '요리괴물'이 오픈한 뉴욕 신상 식당 다녀왔습니다 | Oyatte",
      "date": "6일 전",
      "views": "조회수 14만회",
      "url": "https://youtu.be/XetH267hDeI"
    }
  ],
  "양갱": [],
  "와인킹": [
    {
      "videoId": "k7GZbo0BByg",
      "title": "규제를 조금만 풀어주시면 안될까요?",
      "date": "3일 전",
      "views": "조회수 4.1만회",
      "url": "https://youtu.be/k7GZbo0BByg"
    }
  ],
  "와인 좀 한해": [
    {
      "videoId": "5_saTzUIXkE",
      "title": "와인에 미친 사람들만 모였다 [와인좀한해]",
      "date": "5일 전",
      "views": "조회수 1.4만회",
      "url": "https://youtu.be/5_saTzUIXkE"
    }
  ],
  "이민정 MJ": [
    {
      "videoId": "EkqSyhxmNoY",
      "title": "20년 만에 다시 찾은 로마. 이민정 인생 첫 해방여행 (준후야 서이야 남편아 고마워)",
      "date": "19시간 전",
      "views": "조회수 6.3만회",
      "url": "https://youtu.be/EkqSyhxmNoY"
    },
    {
      "videoId": "aEz8W7QdIfk",
      "title": "엄마 이태리 갔다 온다. 이민정이 준비한 최후의 만찬 *울지 말고 치즈 먹어",
      "date": "7일 전",
      "views": "조회수 12만회",
      "url": "https://youtu.be/aEz8W7QdIfk"
    }
  ],
  "와지트 WAZIT": [
    {
      "videoId": "tkrGO0rigcw",
      "title": "불닭, 엽떡, 닭발에 어울리는 술은?",
      "date": "2일 전",
      "views": "조회수 3.3천회",
      "url": "https://youtu.be/tkrGO0rigcw"
    }
  ],
  "장르가 머니": [],
  "술술워커": [],
  "비노이스타 Vinoista": [],
  "세상의 모든 와인": [
    {
      "videoId": "0tE3u24KMpo",
      "title": "[와인 수입사 소개 #2] 더 뱅 셀렉션",
      "date": "3일 전",
      "views": "조회수 373회",
      "url": "https://youtu.be/0tE3u24KMpo"
    },
    {
      "videoId": "uidpB53vFvY",
      "title": "[20분 완성] 보르도 와인의 모든 것 (좌안 vs 우안,등급체계,포도품종,5대샤또)",
      "date": "7일 전",
      "views": "조회수 671회",
      "url": "https://youtu.be/uidpB53vFvY"
    }
  ],
  "김박사의 와인랩": []
}